{"e86621f47cab4711826e440296572cad":{"id":"e86621f47cab4711826e440296572cad","title":"The Long Dark","description":"The Long Dark","keyImages":[{"type":"DieselGameBox","url":"https://cdn1.epicgames.com/58dfcd1952ee48c1a1fa31c6ace5fe3d/item/EGS_TheLongDark_HinterlandStudioInc_S5-1920x1080-fcfdd407ac1990bec320b49101862585.jpg","md5":"fcfdd407ac1990bec320b49101862585","width":1920,"height":1080,"size":712591,"uploadedDate":"2020-12-14T18:17:43.540Z"},{"type":"DieselGameBoxTall","url":"https://cdn1.epicgames.com/58dfcd1952ee48c1a1fa31c6ace5fe3d/item/EGS_TheLongDark_HinterlandStudioInc_S6-1200x1600-3debfeb01e511b9e1221f973b6bb1fe7.jpg","md5":"3debfeb01e511b9e1221f973b6bb1fe7","width":1200,"height":1600,"size":529403,"uploadedDate":"2020-12-14T18:17:52.961Z"}],"categories":[{"path":"public"},{"path":"games"},{"path":"applications"}],"namespace":"58dfcd1952ee48c1a1fa31c6ace5fe3d","status":"ACTIVE","creationDate":"2020-05-12T21:17:05.157Z","lastModifiedDate":"2022-12-05T21:54:28.819Z","customAttributes":{"CanRunOffline":{"type":"STRING","value":"true"},"PresenceId":{"type":"STRING","value":"58dfcd1952ee48c1a1fa31c6ace5fe3d"},"MonitorPresence":{"type":"STRING","value":"true"},"CloudSaveFolder":{"type":"STRING","value":"{AppData}/Hinterland/TheLongDark/"},"UseAccessControl":{"type":"STRING","value":"false"},"RequirementsJson":{"type":"STRING","value":"[]"},"CanSkipKoreanIdVerification":{"type":"STRING","value":"true"},"MaxSizeMB":{"type":"STRING","value":"1000"},"FolderName":{"type":"STRING","value":"TheLongDark"}},"entitlementName":"e86621f47cab4711826e440296572cad","entitlementType":"EXECUTABLE","itemType":"DURABLE","releaseInfo":[{"id":"7405514b45d54956a9d7ed7d6b98b975","appId":"ed93b18355a84230938c705121c63661","platform":["Windows","Mac"],"dateAdded":"2020-11-02T00:00:00.000Z"}],"developer":"Hinterland Studio","developerId":"o-7defvk4pc8qgqudmkzts63kwttreyu","eulaIds":["egstore"],"endOfSupport":false,"ageGatings":{},"applicationId":"fghi4567hXtV6PLg0d9sRrCOF9RXdwqu","unsearchable":true}}