{"8d95f63859cd4d7496b08ee8e503f624":{"id":"8d95f63859cd4d7496b08ee8e503f624","title":"NBA 2K21","description":"NBA 2K21","keyImages":[{"type":"DieselGameBox","url":"https://cdn1.epicgames.com/salesEvent/salesEvent/EGS_NBA2K21_VisualConcepts_S1_2560x1440-82b12f8e006bdfe848ed548fa9d51a4a","md5":"82b12f8e006bdfe848ed548fa9d51a4a","width":2560,"height":1440,"size":939604,"uploadedDate":"2021-05-20T13:50:48.191Z"},{"type":"DieselGameBoxTall","url":"https://cdn1.epicgames.com/salesEvent/salesEvent/EGS_NBA2K21_VisualConcepts_S2_1200x1600-2fed3198782328f4f59194ebd5e54680","md5":"2fed3198782328f4f59194ebd5e54680","width":1200,"height":1600,"size":625182,"uploadedDate":"2021-05-20T13:51:00.991Z"}],"categories":[{"path":"public"},{"path":"games"},{"path":"applications"}],"namespace":"6b3b9698082c43cd9dcd7f68e3365e79","status":"ACTIVE","creationDate":"2021-01-25T16:29:04.894Z","lastModifiedDate":"2021-05-20T14:00:19.851Z","customAttributes":{"CanRunOffline":{"type":"STRING","value":"true"},"PresenceId":{"type":"STRING","value":"6b3b9698082c43cd9dcd7f68e3365e79"},"MonitorPresence":{"type":"STRING","value":"true"},"UseAccessControl":{"type":"STRING","value":"false"},"RequirementsJson":{"type":"STRING","value":"[]"},"CanSkipKoreanIdVerification":{"type":"STRING","value":"true"},"FolderName":{"type":"STRING","value":"NBA2K21"}},"entitlementName":"8d95f63859cd4d7496b08ee8e503f624","entitlementType":"EXECUTABLE","itemType":"DURABLE","releaseInfo":[{"id":"494dd2f9c5cc48e1b3c7cb4734bf6158","appId":"639977eecfd2497c941b71af949b5067","platform":["Windows"],"dateAdded":"2021-01-25T16:57:07.516Z"}],"developer":"2K Games, Inc.","developerId":"o-37m6jbj5wcvrcvm4wusv7nazdfvbjk","eulaIds":["egstore"],"installModes":[],"endOfSupport":false,"ageGatings":{},"applicationId":"fghi4567o0L0uKrR3cfyyS3RJnBMUMEi","requiresSecureAccount":false,"unsearchable":true}}